chemprop/__init__.py
chemprop/conf.py
chemprop/exceptions.py
chemprop/schedulers.py
chemprop/types.py
chemprop/cli/common.py
chemprop/cli/conf.py
chemprop/cli/convert.py
chemprop/cli/fingerprint.py
chemprop/cli/hpopt.py
chemprop/cli/main.py
chemprop/cli/predict.py
chemprop/cli/train.py
chemprop/cli/utils/MAB_parsing.py
chemprop/cli/utils/__init__.py
chemprop/cli/utils/actions.py
chemprop/cli/utils/args.py
chemprop/cli/utils/command.py
chemprop/cli/utils/parsing.py
chemprop/cli/utils/utils.py
chemprop/data/__init__.py
chemprop/data/collate.py
chemprop/data/dataloader.py
chemprop/data/datapoints.py
chemprop/data/datasets.py
chemprop/data/molgraph.py
chemprop/data/samplers.py
chemprop/data/splitting.py
chemprop/featurizers/__init__.py
chemprop/featurizers/atom.py
chemprop/featurizers/base.py
chemprop/featurizers/bond.py
chemprop/featurizers/molecule.py
chemprop/featurizers/molgraph/__init__.py
chemprop/featurizers/molgraph/cache.py
chemprop/featurizers/molgraph/mixins.py
chemprop/featurizers/molgraph/molecule.py
chemprop/featurizers/molgraph/reaction.py
chemprop/models/__init__.py
chemprop/models/model.py
chemprop/models/mol_atom_bond.py
chemprop/models/multi.py
chemprop/models/utils.py
chemprop/nn/__init__.py
chemprop/nn/agg.py
chemprop/nn/ffn.py
chemprop/nn/hparams.py
chemprop/nn/metrics.py
chemprop/nn/predictors.py
chemprop/nn/transforms.py
chemprop/nn/utils.py
chemprop/nn/message_passing/__init__.py
chemprop/nn/message_passing/base.py
chemprop/nn/message_passing/mixins.py
chemprop/nn/message_passing/mol_atom_bond.py
chemprop/nn/message_passing/multi.py
chemprop/nn/message_passing/proto.py
chemprop/scripts/__init__.py
chemprop/scripts/check_and_install_cuik_molmaker.py
chemprop/uncertainty/__init__.py
chemprop/uncertainty/calibrator.py
chemprop/uncertainty/estimator.py
chemprop/uncertainty/evaluator.py
chemprop/utils/__init__.py
chemprop/utils/registry.py
chemprop/utils/utils.py
chemprop/utils/v1_to_v2.py
chemprop/utils/v2_0_to_v2_1.py
chemprop-2.2.2.dist-info/licenses/LICENSE.txt
chemprop-2.2.2.dist-info/METADATA
chemprop-2.2.2.dist-info/WHEEL
chemprop-2.2.2.dist-info/entry_points.txt
chemprop-2.2.2.dist-info/top_level.txt
chemprop-2.2.2.dist-info/RECORD
