Metadata-Version: 2.4
Name: chemprop
Version: 2.2.2
Summary: Molecular Property Prediction with Message Passing Neural Networks
Author-email: "The Chemprop Development Team (see LICENSE.txt)" <chemprop@mit.edu>
License: MIT
Project-URL: documentation, https://chemprop.readthedocs.io/en/latest/
Project-URL: source, https://github.com/chemprop/chemprop
Project-URL: PyPi, https://pypi.org/project/chemprop/
Keywords: chemistry,machine learning,property prediction,message passing neural network,graph neural network,drug discovery
Classifier: Programming Language :: Python :: 3
Classifier: Programming Language :: Python :: 3.11
Classifier: License :: OSI Approved :: MIT License
Classifier: Operating System :: OS Independent
Requires-Python: >=3.11
License-File: LICENSE.txt
Requires-Dist: lightning>=2.0
Requires-Dist: numpy
Requires-Dist: pandas
Requires-Dist: rdkit
Requires-Dist: scikit-learn
Requires-Dist: scipy
Requires-Dist: torch>=2.1
Requires-Dist: astartes[molecules]
Requires-Dist: ConfigArgParse
Requires-Dist: rich
Requires-Dist: descriptastorus
Provides-Extra: hpopt
Requires-Dist: ray[tune]; extra == "hpopt"
Requires-Dist: hyperopt; extra == "hpopt"
Requires-Dist: optuna; extra == "hpopt"
Requires-Dist: pydantic; extra == "hpopt"
Provides-Extra: dev
Requires-Dist: black==23.*; extra == "dev"
Requires-Dist: bumpversion; extra == "dev"
Requires-Dist: autopep8; extra == "dev"
Requires-Dist: flake8; extra == "dev"
Requires-Dist: pytest; extra == "dev"
Requires-Dist: pytest-cov; extra == "dev"
Requires-Dist: isort; extra == "dev"
Provides-Extra: docs
Requires-Dist: nbsphinx; extra == "docs"
Requires-Dist: sphinx; extra == "docs"
Requires-Dist: sphinx-argparse!=0.5.0; extra == "docs"
Requires-Dist: sphinx-autobuild; extra == "docs"
Requires-Dist: sphinx-autoapi; extra == "docs"
Requires-Dist: sphinxcontrib-bibtex; extra == "docs"
Requires-Dist: sphinx-book-theme; extra == "docs"
Requires-Dist: nbsphinx-link; extra == "docs"
Requires-Dist: ipykernel; extra == "docs"
Requires-Dist: docutils<0.21; extra == "docs"
Requires-Dist: readthedocs-sphinx-ext; extra == "docs"
Requires-Dist: pandoc; extra == "docs"
Provides-Extra: test
Requires-Dist: pytest>=6.2; extra == "test"
Requires-Dist: pytest-cov; extra == "test"
Provides-Extra: notebooks
Requires-Dist: ipykernel; extra == "notebooks"
Requires-Dist: matplotlib; extra == "notebooks"
Dynamic: license-file
